{
  "title": "Heath (Art by @ReynGoldfur)",
  "id": "tg-528140325818990594",
  "net.maunium.telegram.pack": {
    "short_name": "HeathclawStickers",
    "hash": "-1209261291"
  },
  "stickers": [
    {
      "body": "😑 (Heath (Art by @ReynGoldfur))",
      "url": "mxc://matrix.chir.rs/dc1756b014422ca1513f3d78b0813ca0f8e8e4b4",
      "info": {
        "w": 256,
        "h": 256,
        "size": 134026,
        "mimetype": "image/png",
        "thumbnail_url": "mxc://matrix.chir.rs/dc1756b014422ca1513f3d78b0813ca0f8e8e4b4",
        "thumbnail_info": {
          "w": 256,
          "h": 256,
          "size": 134026,
          "mimetype": "image/png"
        }
      },
      "msgtype": "m.sticker",
      "id": "tg-528140325818990695",
      "net.maunium.telegram.sticker": {
        "pack": {
          "id": "528140325818990594",
          "short_name": "HeathclawStickers"
        },
        "id": "528140325818990695",
        "emoticons": [
          "😑"
        ]
      }
    },
    {
      "body": "😅 (Heath (Art by @ReynGoldfur))",
      "url": "mxc://matrix.chir.rs/8ce4686b08112b045b94ddc56ecdc5d2d48019f3",
      "info": {
        "w": 256,
        "h": 256,
        "size": 178914,
        "mimetype": "image/png",
        "thumbnail_url": "mxc://matrix.chir.rs/8ce4686b08112b045b94ddc56ecdc5d2d48019f3",
        "thumbnail_info": {
          "w": 256,
          "h": 256,
          "size": 178914,
          "mimetype": "image/png"
        }
      },
      "msgtype": "m.sticker",
      "id": "tg-528140325818990697",
      "net.maunium.telegram.sticker": {
        "pack": {
          "id": "528140325818990594",
          "short_name": "HeathclawStickers"
        },
        "id": "528140325818990697",
        "emoticons": [
          "😅"
        ]
      }
    },
    {
      "body": "🎲 (Heath (Art by @ReynGoldfur))",
      "url": "mxc://matrix.chir.rs/79fc1dcf5102e9583183f9412872228a6b76e2d3",
      "info": {
        "w": 256,
        "h": 256,
        "size": 203195,
        "mimetype": "image/png",
        "thumbnail_url": "mxc://matrix.chir.rs/79fc1dcf5102e9583183f9412872228a6b76e2d3",
        "thumbnail_info": {
          "w": 256,
          "h": 256,
          "size": 203195,
          "mimetype": "image/png"
        }
      },
      "msgtype": "m.sticker",
      "id": "tg-528140325818990737",
      "net.maunium.telegram.sticker": {
        "pack": {
          "id": "528140325818990594",
          "short_name": "HeathclawStickers"
        },
        "id": "528140325818990737",
        "emoticons": [
          "🎲"
        ]
      }
    },
    {
      "body": "😼 (Heath (Art by @ReynGoldfur))",
      "url": "mxc://matrix.chir.rs/02ab4a4619879d4b88c379d5a5660f61ccc65b2a",
      "info": {
        "w": 256,
        "h": 256,
        "size": 166445,
        "mimetype": "image/png",
        "thumbnail_url": "mxc://matrix.chir.rs/02ab4a4619879d4b88c379d5a5660f61ccc65b2a",
        "thumbnail_info": {
          "w": 256,
          "h": 256,
          "size": 166445,
          "mimetype": "image/png"
        }
      },
      "msgtype": "m.sticker",
      "id": "tg-528140325818990696",
      "net.maunium.telegram.sticker": {
        "pack": {
          "id": "528140325818990594",
          "short_name": "HeathclawStickers"
        },
        "id": "528140325818990696",
        "emoticons": [
          "😼"
        ]
      }
    },
    {
      "body": "🌀 (Heath (Art by @ReynGoldfur))",
      "url": "mxc://matrix.chir.rs/556d905d3d8536133cbe2da7ad64765a31c355f4",
      "info": {
        "w": 256,
        "h": 256,
        "size": 108769,
        "mimetype": "image/png",
        "thumbnail_url": "mxc://matrix.chir.rs/556d905d3d8536133cbe2da7ad64765a31c355f4",
        "thumbnail_info": {
          "w": 256,
          "h": 256,
          "size": 108769,
          "mimetype": "image/png"
        }
      },
      "msgtype": "m.sticker",
      "id": "tg-528140325818990698",
      "net.maunium.telegram.sticker": {
        "pack": {
          "id": "528140325818990594",
          "short_name": "HeathclawStickers"
        },
        "id": "528140325818990698",
        "emoticons": [
          "🌀"
        ]
      }
    },
    {
      "body": "😼 (Heath (Art by @ReynGoldfur))",
      "url": "mxc://matrix.chir.rs/0fd451615317b8a6a512cc5a00f275c4d45377ae",
      "info": {
        "w": 256,
        "h": 256,
        "size": 122808,
        "mimetype": "image/png",
        "thumbnail_url": "mxc://matrix.chir.rs/0fd451615317b8a6a512cc5a00f275c4d45377ae",
        "thumbnail_info": {
          "w": 256,
          "h": 256,
          "size": 122808,
          "mimetype": "image/png"
        }
      },
      "msgtype": "m.sticker",
      "id": "tg-528140325818990701",
      "net.maunium.telegram.sticker": {
        "pack": {
          "id": "528140325818990594",
          "short_name": "HeathclawStickers"
        },
        "id": "528140325818990701",
        "emoticons": [
          "😼"
        ]
      }
    },
    {
      "body": "👅 (Heath (Art by @ReynGoldfur))",
      "url": "mxc://matrix.chir.rs/2dc6631aec88d7c0a830fe7aab2246f47ca27adf",
      "info": {
        "w": 256,
        "h": 256,
        "size": 156473,
        "mimetype": "image/png",
        "thumbnail_url": "mxc://matrix.chir.rs/2dc6631aec88d7c0a830fe7aab2246f47ca27adf",
        "thumbnail_info": {
          "w": 256,
          "h": 256,
          "size": 156473,
          "mimetype": "image/png"
        }
      },
      "msgtype": "m.sticker",
      "id": "tg-528140325818990702",
      "net.maunium.telegram.sticker": {
        "pack": {
          "id": "528140325818990594",
          "short_name": "HeathclawStickers"
        },
        "id": "528140325818990702",
        "emoticons": [
          "👅"
        ]
      }
    },
    {
      "body": "👅 (Heath (Art by @ReynGoldfur))",
      "url": "mxc://matrix.chir.rs/51bc1881b607274b1c4559a033538dce32e9d217",
      "info": {
        "w": 256,
        "h": 256,
        "size": 182942,
        "mimetype": "image/png",
        "thumbnail_url": "mxc://matrix.chir.rs/51bc1881b607274b1c4559a033538dce32e9d217",
        "thumbnail_info": {
          "w": 256,
          "h": 256,
          "size": 182942,
          "mimetype": "image/png"
        }
      },
      "msgtype": "m.sticker",
      "id": "tg-528140325818990703",
      "net.maunium.telegram.sticker": {
        "pack": {
          "id": "528140325818990594",
          "short_name": "HeathclawStickers"
        },
        "id": "528140325818990703",
        "emoticons": [
          "👅"
        ]
      }
    },
    {
      "body": "❤️ (Heath (Art by @ReynGoldfur))",
      "url": "mxc://matrix.chir.rs/e4ff10b74df5efe5565e45228ae64e13ced79082",
      "info": {
        "w": 256,
        "h": 256,
        "size": 138146,
        "mimetype": "image/png",
        "thumbnail_url": "mxc://matrix.chir.rs/e4ff10b74df5efe5565e45228ae64e13ced79082",
        "thumbnail_info": {
          "w": 256,
          "h": 256,
          "size": 138146,
          "mimetype": "image/png"
        }
      },
      "msgtype": "m.sticker",
      "id": "tg-528140325818990704",
      "net.maunium.telegram.sticker": {
        "pack": {
          "id": "528140325818990594",
          "short_name": "HeathclawStickers"
        },
        "id": "528140325818990704",
        "emoticons": [
          "❤"
        ]
      }
    },
    {
      "body": "😌 (Heath (Art by @ReynGoldfur))",
      "url": "mxc://matrix.chir.rs/148446f377289af9176a94494d46fc1dfb0b990e",
      "info": {
        "w": 256,
        "h": 256,
        "size": 105936,
        "mimetype": "image/png",
        "thumbnail_url": "mxc://matrix.chir.rs/148446f377289af9176a94494d46fc1dfb0b990e",
        "thumbnail_info": {
          "w": 256,
          "h": 256,
          "size": 105936,
          "mimetype": "image/png"
        }
      },
      "msgtype": "m.sticker",
      "id": "tg-528140325818990705",
      "net.maunium.telegram.sticker": {
        "pack": {
          "id": "528140325818990594",
          "short_name": "HeathclawStickers"
        },
        "id": "528140325818990705",
        "emoticons": [
          "😌"
        ]
      }
    },
    {
      "body": "🤗 (Heath (Art by @ReynGoldfur))",
      "url": "mxc://matrix.chir.rs/0330ec474ef2b42da62ede04ffd6b375d8dd048b",
      "info": {
        "w": 256,
        "h": 256,
        "size": 122385,
        "mimetype": "image/png",
        "thumbnail_url": "mxc://matrix.chir.rs/0330ec474ef2b42da62ede04ffd6b375d8dd048b",
        "thumbnail_info": {
          "w": 256,
          "h": 256,
          "size": 122385,
          "mimetype": "image/png"
        }
      },
      "msgtype": "m.sticker",
      "id": "tg-528140325818990706",
      "net.maunium.telegram.sticker": {
        "pack": {
          "id": "528140325818990594",
          "short_name": "HeathclawStickers"
        },
        "id": "528140325818990706",
        "emoticons": [
          "🤗"
        ]
      }
    },
    {
      "body": "☺️ (Heath (Art by @ReynGoldfur))",
      "url": "mxc://matrix.chir.rs/733c043579e82f2cccbd7251073589d6a9cb8620",
      "info": {
        "w": 256,
        "h": 256,
        "size": 120806,
        "mimetype": "image/png",
        "thumbnail_url": "mxc://matrix.chir.rs/733c043579e82f2cccbd7251073589d6a9cb8620",
        "thumbnail_info": {
          "w": 256,
          "h": 256,
          "size": 120806,
          "mimetype": "image/png"
        }
      },
      "msgtype": "m.sticker",
      "id": "tg-528140325818990707",
      "net.maunium.telegram.sticker": {
        "pack": {
          "id": "528140325818990594",
          "short_name": "HeathclawStickers"
        },
        "id": "528140325818990707",
        "emoticons": [
          "☺"
        ]
      }
    },
    {
      "body": "😳 (Heath (Art by @ReynGoldfur))",
      "url": "mxc://matrix.chir.rs/9ee84904e32579b4f0bcc2d58d453a2a40086b89",
      "info": {
        "w": 256,
        "h": 256,
        "size": 104470,
        "mimetype": "image/png",
        "thumbnail_url": "mxc://matrix.chir.rs/9ee84904e32579b4f0bcc2d58d453a2a40086b89",
        "thumbnail_info": {
          "w": 256,
          "h": 256,
          "size": 104470,
          "mimetype": "image/png"
        }
      },
      "msgtype": "m.sticker",
      "id": "tg-528140325818990699",
      "net.maunium.telegram.sticker": {
        "pack": {
          "id": "528140325818990594",
          "short_name": "HeathclawStickers"
        },
        "id": "528140325818990699",
        "emoticons": [
          "😳"
        ]
      }
    },
    {
      "body": "💦 (Heath (Art by @ReynGoldfur))",
      "url": "mxc://matrix.chir.rs/53b41fbe39dc1e93a17b03263957236db06ec7fc",
      "info": {
        "w": 256,
        "h": 256,
        "size": 167747,
        "mimetype": "image/png",
        "thumbnail_url": "mxc://matrix.chir.rs/53b41fbe39dc1e93a17b03263957236db06ec7fc",
        "thumbnail_info": {
          "w": 256,
          "h": 256,
          "size": 167747,
          "mimetype": "image/png"
        }
      },
      "msgtype": "m.sticker",
      "id": "tg-528140325818990708",
      "net.maunium.telegram.sticker": {
        "pack": {
          "id": "528140325818990594",
          "short_name": "HeathclawStickers"
        },
        "id": "528140325818990708",
        "emoticons": [
          "💦"
        ]
      }
    },
    {
      "body": "😓 (Heath (Art by @ReynGoldfur))",
      "url": "mxc://matrix.chir.rs/04ed18fbb72f96ced3b2cd43e401aaaee5ace45e",
      "info": {
        "w": 256,
        "h": 256,
        "size": 138347,
        "mimetype": "image/png",
        "thumbnail_url": "mxc://matrix.chir.rs/04ed18fbb72f96ced3b2cd43e401aaaee5ace45e",
        "thumbnail_info": {
          "w": 256,
          "h": 256,
          "size": 138347,
          "mimetype": "image/png"
        }
      },
      "msgtype": "m.sticker",
      "id": "tg-528140325818990726",
      "net.maunium.telegram.sticker": {
        "pack": {
          "id": "528140325818990594",
          "short_name": "HeathclawStickers"
        },
        "id": "528140325818990726",
        "emoticons": [
          "😓"
        ]
      }
    },
    {
      "body": "😯 (Heath (Art by @ReynGoldfur))",
      "url": "mxc://matrix.chir.rs/c24fc0372d24e019edb73b914dbc77fa415a10f5",
      "info": {
        "w": 256,
        "h": 256,
        "size": 99000,
        "mimetype": "image/png",
        "thumbnail_url": "mxc://matrix.chir.rs/c24fc0372d24e019edb73b914dbc77fa415a10f5",
        "thumbnail_info": {
          "w": 256,
          "h": 256,
          "size": 99000,
          "mimetype": "image/png"
        }
      },
      "msgtype": "m.sticker",
      "id": "tg-528140325818990712",
      "net.maunium.telegram.sticker": {
        "pack": {
          "id": "528140325818990594",
          "short_name": "HeathclawStickers"
        },
        "id": "528140325818990712",
        "emoticons": [
          "😯"
        ]
      }
    },
    {
      "body": "☺️ (Heath (Art by @ReynGoldfur))",
      "url": "mxc://matrix.chir.rs/22f85eed3703f88e7f3f28033a95c6a4b2e22f83",
      "info": {
        "w": 256,
        "h": 256,
        "size": 101613,
        "mimetype": "image/png",
        "thumbnail_url": "mxc://matrix.chir.rs/22f85eed3703f88e7f3f28033a95c6a4b2e22f83",
        "thumbnail_info": {
          "w": 256,
          "h": 256,
          "size": 101613,
          "mimetype": "image/png"
        }
      },
      "msgtype": "m.sticker",
      "id": "tg-528140325818990713",
      "net.maunium.telegram.sticker": {
        "pack": {
          "id": "528140325818990594",
          "short_name": "HeathclawStickers"
        },
        "id": "528140325818990713",
        "emoticons": [
          "☺"
        ]
      }
    },
    {
      "body": "😳 (Heath (Art by @ReynGoldfur))",
      "url": "mxc://matrix.chir.rs/88b49bc58f3cdd5c2f166b5925648058f7c3bb95",
      "info": {
        "w": 256,
        "h": 256,
        "size": 118183,
        "mimetype": "image/png",
        "thumbnail_url": "mxc://matrix.chir.rs/88b49bc58f3cdd5c2f166b5925648058f7c3bb95",
        "thumbnail_info": {
          "w": 256,
          "h": 256,
          "size": 118183,
          "mimetype": "image/png"
        }
      },
      "msgtype": "m.sticker",
      "id": "tg-528140325818990727",
      "net.maunium.telegram.sticker": {
        "pack": {
          "id": "528140325818990594",
          "short_name": "HeathclawStickers"
        },
        "id": "528140325818990727",
        "emoticons": [
          "😳"
        ]
      }
    },
    {
      "body": "😇 (Heath (Art by @ReynGoldfur))",
      "url": "mxc://matrix.chir.rs/d1a141afcc1a4b778596975eeefcc862db6566b5",
      "info": {
        "w": 256,
        "h": 256,
        "size": 143570,
        "mimetype": "image/png",
        "thumbnail_url": "mxc://matrix.chir.rs/d1a141afcc1a4b778596975eeefcc862db6566b5",
        "thumbnail_info": {
          "w": 256,
          "h": 256,
          "size": 143570,
          "mimetype": "image/png"
        }
      },
      "msgtype": "m.sticker",
      "id": "tg-528140325818990710",
      "net.maunium.telegram.sticker": {
        "pack": {
          "id": "528140325818990594",
          "short_name": "HeathclawStickers"
        },
        "id": "528140325818990710",
        "emoticons": [
          "😇"
        ]
      }
    },
    {
      "body": "😒 (Heath (Art by @ReynGoldfur))",
      "url": "mxc://matrix.chir.rs/39b63282094a7fecb6e1afabd9a026be1f074ad4",
      "info": {
        "w": 256,
        "h": 256,
        "size": 95142,
        "mimetype": "image/png",
        "thumbnail_url": "mxc://matrix.chir.rs/39b63282094a7fecb6e1afabd9a026be1f074ad4",
        "thumbnail_info": {
          "w": 256,
          "h": 256,
          "size": 95142,
          "mimetype": "image/png"
        }
      },
      "msgtype": "m.sticker",
      "id": "tg-528140325818990709",
      "net.maunium.telegram.sticker": {
        "pack": {
          "id": "528140325818990594",
          "short_name": "HeathclawStickers"
        },
        "id": "528140325818990709",
        "emoticons": [
          "😒"
        ]
      }
    },
    {
      "body": "😠 (Heath (Art by @ReynGoldfur))",
      "url": "mxc://matrix.chir.rs/698b75d8510a2967a076c7030a624d30c8ac8779",
      "info": {
        "w": 256,
        "h": 256,
        "size": 160965,
        "mimetype": "image/png",
        "thumbnail_url": "mxc://matrix.chir.rs/698b75d8510a2967a076c7030a624d30c8ac8779",
        "thumbnail_info": {
          "w": 256,
          "h": 256,
          "size": 160965,
          "mimetype": "image/png"
        }
      },
      "msgtype": "m.sticker",
      "id": "tg-528140325818990711",
      "net.maunium.telegram.sticker": {
        "pack": {
          "id": "528140325818990594",
          "short_name": "HeathclawStickers"
        },
        "id": "528140325818990711",
        "emoticons": [
          "😠"
        ]
      }
    },
    {
      "body": "😉 (Heath (Art by @ReynGoldfur))",
      "url": "mxc://matrix.chir.rs/0ea1cd5a7ac31116eeb9ca3779cd06b7b6db0fbc",
      "info": {
        "w": 256,
        "h": 256,
        "size": 111624,
        "mimetype": "image/png",
        "thumbnail_url": "mxc://matrix.chir.rs/0ea1cd5a7ac31116eeb9ca3779cd06b7b6db0fbc",
        "thumbnail_info": {
          "w": 256,
          "h": 256,
          "size": 111624,
          "mimetype": "image/png"
        }
      },
      "msgtype": "m.sticker",
      "id": "tg-528140325818990714",
      "net.maunium.telegram.sticker": {
        "pack": {
          "id": "528140325818990594",
          "short_name": "HeathclawStickers"
        },
        "id": "528140325818990714",
        "emoticons": [
          "😉"
        ]
      }
    },
    {
      "body": "💤 (Heath (Art by @ReynGoldfur))",
      "url": "mxc://matrix.chir.rs/3eaf1d4dbc4aa02536594fdd7e9c3e2e964d50cc",
      "info": {
        "w": 256,
        "h": 256,
        "size": 121153,
        "mimetype": "image/png",
        "thumbnail_url": "mxc://matrix.chir.rs/3eaf1d4dbc4aa02536594fdd7e9c3e2e964d50cc",
        "thumbnail_info": {
          "w": 256,
          "h": 256,
          "size": 121153,
          "mimetype": "image/png"
        }
      },
      "msgtype": "m.sticker",
      "id": "tg-528140325818990715",
      "net.maunium.telegram.sticker": {
        "pack": {
          "id": "528140325818990594",
          "short_name": "HeathclawStickers"
        },
        "id": "528140325818990715",
        "emoticons": [
          "💤"
        ]
      }
    },
    {
      "body": "😼 (Heath (Art by @ReynGoldfur))",
      "url": "mxc://matrix.chir.rs/5fd2724adcddea7282d084fd549e7741d517d46c",
      "info": {
        "w": 256,
        "h": 256,
        "size": 95660,
        "mimetype": "image/png",
        "thumbnail_url": "mxc://matrix.chir.rs/5fd2724adcddea7282d084fd549e7741d517d46c",
        "thumbnail_info": {
          "w": 256,
          "h": 256,
          "size": 95660,
          "mimetype": "image/png"
        }
      },
      "msgtype": "m.sticker",
      "id": "tg-528140325818990716",
      "net.maunium.telegram.sticker": {
        "pack": {
          "id": "528140325818990594",
          "short_name": "HeathclawStickers"
        },
        "id": "528140325818990716",
        "emoticons": [
          "😼"
        ]
      }
    },
    {
      "body": "🤦‍♂️ (Heath (Art by @ReynGoldfur))",
      "url": "mxc://matrix.chir.rs/36cdab2593cd7b7f73331afa85b9225cf3b9a2f2",
      "info": {
        "w": 256,
        "h": 256,
        "size": 105816,
        "mimetype": "image/png",
        "thumbnail_url": "mxc://matrix.chir.rs/36cdab2593cd7b7f73331afa85b9225cf3b9a2f2",
        "thumbnail_info": {
          "w": 256,
          "h": 256,
          "size": 105816,
          "mimetype": "image/png"
        }
      },
      "msgtype": "m.sticker",
      "id": "tg-528140325818990717",
      "net.maunium.telegram.sticker": {
        "pack": {
          "id": "528140325818990594",
          "short_name": "HeathclawStickers"
        },
        "id": "528140325818990717",
        "emoticons": [
          "🤦‍♂"
        ]
      }
    },
    {
      "body": "😵 (Heath (Art by @ReynGoldfur))",
      "url": "mxc://matrix.chir.rs/cecdd830db468fee05cca9f458032c739a3d3033",
      "info": {
        "w": 256,
        "h": 256,
        "size": 70956,
        "mimetype": "image/png",
        "thumbnail_url": "mxc://matrix.chir.rs/cecdd830db468fee05cca9f458032c739a3d3033",
        "thumbnail_info": {
          "w": 256,
          "h": 256,
          "size": 70956,
          "mimetype": "image/png"
        }
      },
      "msgtype": "m.sticker",
      "id": "tg-528140325818990718",
      "net.maunium.telegram.sticker": {
        "pack": {
          "id": "528140325818990594",
          "short_name": "HeathclawStickers"
        },
        "id": "528140325818990718",
        "emoticons": [
          "😵"
        ]
      }
    },
    {
      "body": "🙁 (Heath (Art by @ReynGoldfur))",
      "url": "mxc://matrix.chir.rs/bc08780b80a640cec58660aa170b8c2ac7be4953",
      "info": {
        "w": 256,
        "h": 256,
        "size": 84698,
        "mimetype": "image/png",
        "thumbnail_url": "mxc://matrix.chir.rs/bc08780b80a640cec58660aa170b8c2ac7be4953",
        "thumbnail_info": {
          "w": 256,
          "h": 256,
          "size": 84698,
          "mimetype": "image/png"
        }
      },
      "msgtype": "m.sticker",
      "id": "tg-528140325818990719",
      "net.maunium.telegram.sticker": {
        "pack": {
          "id": "528140325818990594",
          "short_name": "HeathclawStickers"
        },
        "id": "528140325818990719",
        "emoticons": [
          "🙁"
        ]
      }
    },
    {
      "body": "👅 (Heath (Art by @ReynGoldfur))",
      "url": "mxc://matrix.chir.rs/6140762ed8fb8138f2bfd89ec09e752eb51090da",
      "info": {
        "w": 256,
        "h": 256,
        "size": 151765,
        "mimetype": "image/png",
        "thumbnail_url": "mxc://matrix.chir.rs/6140762ed8fb8138f2bfd89ec09e752eb51090da",
        "thumbnail_info": {
          "w": 256,
          "h": 256,
          "size": 151765,
          "mimetype": "image/png"
        }
      },
      "msgtype": "m.sticker",
      "id": "tg-528140325818990720",
      "net.maunium.telegram.sticker": {
        "pack": {
          "id": "528140325818990594",
          "short_name": "HeathclawStickers"
        },
        "id": "528140325818990720",
        "emoticons": [
          "👅"
        ]
      }
    },
    {
      "body": "🍻 (Heath (Art by @ReynGoldfur))",
      "url": "mxc://matrix.chir.rs/0855ed8d1fdc9e9b092c2346857e00458792fec2",
      "info": {
        "w": 256,
        "h": 256,
        "size": 170919,
        "mimetype": "image/png",
        "thumbnail_url": "mxc://matrix.chir.rs/0855ed8d1fdc9e9b092c2346857e00458792fec2",
        "thumbnail_info": {
          "w": 256,
          "h": 256,
          "size": 170919,
          "mimetype": "image/png"
        }
      },
      "msgtype": "m.sticker",
      "id": "tg-528140325818990721",
      "net.maunium.telegram.sticker": {
        "pack": {
          "id": "528140325818990594",
          "short_name": "HeathclawStickers"
        },
        "id": "528140325818990721",
        "emoticons": [
          "🍻"
        ]
      }
    },
    {
      "body": "🤩 (Heath (Art by @ReynGoldfur))",
      "url": "mxc://matrix.chir.rs/5f0e7047ee1097999ea1f25068061a3e542c54d9",
      "info": {
        "w": 256,
        "h": 256,
        "size": 136045,
        "mimetype": "image/png",
        "thumbnail_url": "mxc://matrix.chir.rs/5f0e7047ee1097999ea1f25068061a3e542c54d9",
        "thumbnail_info": {
          "w": 256,
          "h": 256,
          "size": 136045,
          "mimetype": "image/png"
        }
      },
      "msgtype": "m.sticker",
      "id": "tg-528140325818990722",
      "net.maunium.telegram.sticker": {
        "pack": {
          "id": "528140325818990594",
          "short_name": "HeathclawStickers"
        },
        "id": "528140325818990722",
        "emoticons": [
          "🤩"
        ]
      }
    },
    {
      "body": "🔪 (Heath (Art by @ReynGoldfur))",
      "url": "mxc://matrix.chir.rs/350505a47f082b8b0efe04a13a279d858c39817e",
      "info": {
        "w": 256,
        "h": 256,
        "size": 166796,
        "mimetype": "image/png",
        "thumbnail_url": "mxc://matrix.chir.rs/350505a47f082b8b0efe04a13a279d858c39817e",
        "thumbnail_info": {
          "w": 256,
          "h": 256,
          "size": 166796,
          "mimetype": "image/png"
        }
      },
      "msgtype": "m.sticker",
      "id": "tg-528140325818990723",
      "net.maunium.telegram.sticker": {
        "pack": {
          "id": "528140325818990594",
          "short_name": "HeathclawStickers"
        },
        "id": "528140325818990723",
        "emoticons": [
          "🔪"
        ]
      }
    },
    {
      "body": "😅 (Heath (Art by @ReynGoldfur))",
      "url": "mxc://matrix.chir.rs/05ca42b7b6d505a1130e201a4d5065040bd346df",
      "info": {
        "w": 256,
        "h": 256,
        "size": 176076,
        "mimetype": "image/png",
        "thumbnail_url": "mxc://matrix.chir.rs/05ca42b7b6d505a1130e201a4d5065040bd346df",
        "thumbnail_info": {
          "w": 256,
          "h": 256,
          "size": 176076,
          "mimetype": "image/png"
        }
      },
      "msgtype": "m.sticker",
      "id": "tg-528140325818990724",
      "net.maunium.telegram.sticker": {
        "pack": {
          "id": "528140325818990594",
          "short_name": "HeathclawStickers"
        },
        "id": "528140325818990724",
        "emoticons": [
          "😅"
        ]
      }
    },
    {
      "body": "🤬 (Heath (Art by @ReynGoldfur))",
      "url": "mxc://matrix.chir.rs/8106187f42715284cacc367fc743756dce1b4214",
      "info": {
        "w": 256,
        "h": 256,
        "size": 279788,
        "mimetype": "image/png",
        "thumbnail_url": "mxc://matrix.chir.rs/8106187f42715284cacc367fc743756dce1b4214",
        "thumbnail_info": {
          "w": 256,
          "h": 256,
          "size": 279788,
          "mimetype": "image/png"
        }
      },
      "msgtype": "m.sticker",
      "id": "tg-528140325818990725",
      "net.maunium.telegram.sticker": {
        "pack": {
          "id": "528140325818990594",
          "short_name": "HeathclawStickers"
        },
        "id": "528140325818990725",
        "emoticons": [
          "🤬"
        ]
      }
    },
    {
      "body": "😖 (Heath (Art by @ReynGoldfur))",
      "url": "mxc://matrix.chir.rs/5a48dc7e40665aeac0dc81095435d316c8ffd063",
      "info": {
        "w": 256,
        "h": 256,
        "size": 82150,
        "mimetype": "image/png",
        "thumbnail_url": "mxc://matrix.chir.rs/5a48dc7e40665aeac0dc81095435d316c8ffd063",
        "thumbnail_info": {
          "w": 256,
          "h": 256,
          "size": 82150,
          "mimetype": "image/png"
        }
      },
      "msgtype": "m.sticker",
      "id": "tg-528140325818990728",
      "net.maunium.telegram.sticker": {
        "pack": {
          "id": "528140325818990594",
          "short_name": "HeathclawStickers"
        },
        "id": "528140325818990728",
        "emoticons": [
          "😖"
        ]
      }
    },
    {
      "body": "🏹 (Heath (Art by @ReynGoldfur))",
      "url": "mxc://matrix.chir.rs/25a98817a3bd7d6082c01d705c26a3229acd8f46",
      "info": {
        "w": 256,
        "h": 256,
        "size": 198832,
        "mimetype": "image/png",
        "thumbnail_url": "mxc://matrix.chir.rs/25a98817a3bd7d6082c01d705c26a3229acd8f46",
        "thumbnail_info": {
          "w": 256,
          "h": 256,
          "size": 198832,
          "mimetype": "image/png"
        }
      },
      "msgtype": "m.sticker",
      "id": "tg-528140325818990729",
      "net.maunium.telegram.sticker": {
        "pack": {
          "id": "528140325818990594",
          "short_name": "HeathclawStickers"
        },
        "id": "528140325818990729",
        "emoticons": [
          "🏹"
        ]
      }
    },
    {
      "body": "😺 (Heath (Art by @ReynGoldfur))",
      "url": "mxc://matrix.chir.rs/4ea0859a79bf2d7e9a2db2c5c2d6ef38d90af4d3",
      "info": {
        "w": 256,
        "h": 256,
        "size": 111397,
        "mimetype": "image/png",
        "thumbnail_url": "mxc://matrix.chir.rs/4ea0859a79bf2d7e9a2db2c5c2d6ef38d90af4d3",
        "thumbnail_info": {
          "w": 256,
          "h": 256,
          "size": 111397,
          "mimetype": "image/png"
        }
      },
      "msgtype": "m.sticker",
      "id": "tg-528140325818990730",
      "net.maunium.telegram.sticker": {
        "pack": {
          "id": "528140325818990594",
          "short_name": "HeathclawStickers"
        },
        "id": "528140325818990730",
        "emoticons": [
          "😺"
        ]
      }
    },
    {
      "body": "❗️ (Heath (Art by @ReynGoldfur))",
      "url": "mxc://matrix.chir.rs/91853436a413807c604c341fb29ab1a7a943665c",
      "info": {
        "w": 256,
        "h": 256,
        "size": 88623,
        "mimetype": "image/png",
        "thumbnail_url": "mxc://matrix.chir.rs/91853436a413807c604c341fb29ab1a7a943665c",
        "thumbnail_info": {
          "w": 256,
          "h": 256,
          "size": 88623,
          "mimetype": "image/png"
        }
      },
      "msgtype": "m.sticker",
      "id": "tg-528140325818990731",
      "net.maunium.telegram.sticker": {
        "pack": {
          "id": "528140325818990594",
          "short_name": "HeathclawStickers"
        },
        "id": "528140325818990731",
        "emoticons": [
          "❗"
        ]
      }
    },
    {
      "body": "✨ (Heath (Art by @ReynGoldfur))",
      "url": "mxc://matrix.chir.rs/cf36f063850a2c57d14d0e06c04d03dabfe918da",
      "info": {
        "w": 256,
        "h": 256,
        "size": 74159,
        "mimetype": "image/png",
        "thumbnail_url": "mxc://matrix.chir.rs/cf36f063850a2c57d14d0e06c04d03dabfe918da",
        "thumbnail_info": {
          "w": 256,
          "h": 256,
          "size": 74159,
          "mimetype": "image/png"
        }
      },
      "msgtype": "m.sticker",
      "id": "tg-528140325818990732",
      "net.maunium.telegram.sticker": {
        "pack": {
          "id": "528140325818990594",
          "short_name": "HeathclawStickers"
        },
        "id": "528140325818990732",
        "emoticons": [
          "✨"
        ]
      }
    },
    {
      "body": "🤤 (Heath (Art by @ReynGoldfur))",
      "url": "mxc://matrix.chir.rs/d54103f97ecb8b5a71fc3f61ec2a86e9e5d9221a",
      "info": {
        "w": 256,
        "h": 256,
        "size": 90731,
        "mimetype": "image/png",
        "thumbnail_url": "mxc://matrix.chir.rs/d54103f97ecb8b5a71fc3f61ec2a86e9e5d9221a",
        "thumbnail_info": {
          "w": 256,
          "h": 256,
          "size": 90731,
          "mimetype": "image/png"
        }
      },
      "msgtype": "m.sticker",
      "id": "tg-528140325818990733",
      "net.maunium.telegram.sticker": {
        "pack": {
          "id": "528140325818990594",
          "short_name": "HeathclawStickers"
        },
        "id": "528140325818990733",
        "emoticons": [
          "🤤"
        ]
      }
    },
    {
      "body": "😘 (Heath (Art by @ReynGoldfur))",
      "url": "mxc://matrix.chir.rs/0a7e1ef1328ae1085720dd246c672a92f2f8d703",
      "info": {
        "w": 256,
        "h": 256,
        "size": 97044,
        "mimetype": "image/png",
        "thumbnail_url": "mxc://matrix.chir.rs/0a7e1ef1328ae1085720dd246c672a92f2f8d703",
        "thumbnail_info": {
          "w": 256,
          "h": 256,
          "size": 97044,
          "mimetype": "image/png"
        }
      },
      "msgtype": "m.sticker",
      "id": "tg-528140325818990734",
      "net.maunium.telegram.sticker": {
        "pack": {
          "id": "528140325818990594",
          "short_name": "HeathclawStickers"
        },
        "id": "528140325818990734",
        "emoticons": [
          "😘"
        ]
      }
    },
    {
      "body": "😺 (Heath (Art by @ReynGoldfur))",
      "url": "mxc://matrix.chir.rs/f6f8a8f9a21486072bd61782581e424e5615042a",
      "info": {
        "w": 256,
        "h": 256,
        "size": 164058,
        "mimetype": "image/png",
        "thumbnail_url": "mxc://matrix.chir.rs/f6f8a8f9a21486072bd61782581e424e5615042a",
        "thumbnail_info": {
          "w": 256,
          "h": 256,
          "size": 164058,
          "mimetype": "image/png"
        }
      },
      "msgtype": "m.sticker",
      "id": "tg-528140325818990735",
      "net.maunium.telegram.sticker": {
        "pack": {
          "id": "528140325818990594",
          "short_name": "HeathclawStickers"
        },
        "id": "528140325818990735",
        "emoticons": [
          "😺"
        ]
      }
    },
    {
      "body": "💤 (Heath (Art by @ReynGoldfur))",
      "url": "mxc://matrix.chir.rs/18e51b95790862682b49c37023706c61fbe734ab",
      "info": {
        "w": 256,
        "h": 256,
        "size": 40817,
        "mimetype": "image/png",
        "thumbnail_url": "mxc://matrix.chir.rs/18e51b95790862682b49c37023706c61fbe734ab",
        "thumbnail_info": {
          "w": 256,
          "h": 256,
          "size": 40817,
          "mimetype": "image/png"
        }
      },
      "msgtype": "m.sticker",
      "id": "tg-528140325818990736",
      "net.maunium.telegram.sticker": {
        "pack": {
          "id": "528140325818990594",
          "short_name": "HeathclawStickers"
        },
        "id": "528140325818990736",
        "emoticons": [
          "💤"
        ]
      }
    },
    {
      "body": "😠 (Heath (Art by @ReynGoldfur))",
      "url": "mxc://matrix.chir.rs/762f971289eb742a6e0c1ed3b147cd26f2171042",
      "info": {
        "w": 256,
        "h": 256,
        "size": 120243,
        "mimetype": "image/png",
        "thumbnail_url": "mxc://matrix.chir.rs/762f971289eb742a6e0c1ed3b147cd26f2171042",
        "thumbnail_info": {
          "w": 256,
          "h": 256,
          "size": 120243,
          "mimetype": "image/png"
        }
      },
      "msgtype": "m.sticker",
      "id": "tg-528140325818990738",
      "net.maunium.telegram.sticker": {
        "pack": {
          "id": "528140325818990594",
          "short_name": "HeathclawStickers"
        },
        "id": "528140325818990738",
        "emoticons": [
          "😠"
        ]
      }
    },
    {
      "body": "❓ (Heath (Art by @ReynGoldfur))",
      "url": "mxc://matrix.chir.rs/c16689474d44984d1fb8cb82efafee6ee406eac5",
      "info": {
        "w": 256,
        "h": 256,
        "size": 100190,
        "mimetype": "image/png",
        "thumbnail_url": "mxc://matrix.chir.rs/c16689474d44984d1fb8cb82efafee6ee406eac5",
        "thumbnail_info": {
          "w": 256,
          "h": 256,
          "size": 100190,
          "mimetype": "image/png"
        }
      },
      "msgtype": "m.sticker",
      "id": "tg-528140325818990739",
      "net.maunium.telegram.sticker": {
        "pack": {
          "id": "528140325818990594",
          "short_name": "HeathclawStickers"
        },
        "id": "528140325818990739",
        "emoticons": [
          "❓"
        ]
      }
    },
    {
      "body": "💦 (Heath (Art by @ReynGoldfur))",
      "url": "mxc://matrix.chir.rs/d25ae387e8ceea25cf80c42d5376057b6d46ad22",
      "info": {
        "w": 256,
        "h": 256,
        "size": 135680,
        "mimetype": "image/png",
        "thumbnail_url": "mxc://matrix.chir.rs/d25ae387e8ceea25cf80c42d5376057b6d46ad22",
        "thumbnail_info": {
          "w": 256,
          "h": 256,
          "size": 135680,
          "mimetype": "image/png"
        }
      },
      "msgtype": "m.sticker",
      "id": "tg-528140325818990740",
      "net.maunium.telegram.sticker": {
        "pack": {
          "id": "528140325818990594",
          "short_name": "HeathclawStickers"
        },
        "id": "528140325818990740",
        "emoticons": [
          "💦"
        ]
      }
    },
    {
      "body": "👎 (Heath (Art by @ReynGoldfur))",
      "url": "mxc://matrix.chir.rs/9881a730cdfbdb5c605f0c8ba59ce5ee36aca7eb",
      "info": {
        "w": 256,
        "h": 256,
        "size": 97440,
        "mimetype": "image/png",
        "thumbnail_url": "mxc://matrix.chir.rs/9881a730cdfbdb5c605f0c8ba59ce5ee36aca7eb",
        "thumbnail_info": {
          "w": 256,
          "h": 256,
          "size": 97440,
          "mimetype": "image/png"
        }
      },
      "msgtype": "m.sticker",
      "id": "tg-528140325818990741",
      "net.maunium.telegram.sticker": {
        "pack": {
          "id": "528140325818990594",
          "short_name": "HeathclawStickers"
        },
        "id": "528140325818990741",
        "emoticons": [
          "👎"
        ]
      }
    },
    {
      "body": "😳 (Heath (Art by @ReynGoldfur))",
      "url": "mxc://matrix.chir.rs/5a59d9f68c5822e1d0094b78e3dd53920356aa84",
      "info": {
        "w": 256,
        "h": 256,
        "size": 87072,
        "mimetype": "image/png",
        "thumbnail_url": "mxc://matrix.chir.rs/5a59d9f68c5822e1d0094b78e3dd53920356aa84",
        "thumbnail_info": {
          "w": 256,
          "h": 256,
          "size": 87072,
          "mimetype": "image/png"
        }
      },
      "msgtype": "m.sticker",
      "id": "tg-528140325818990742",
      "net.maunium.telegram.sticker": {
        "pack": {
          "id": "528140325818990594",
          "short_name": "HeathclawStickers"
        },
        "id": "528140325818990742",
        "emoticons": [
          "😳"
        ]
      }
    },
    {
      "body": "😝 (Heath (Art by @ReynGoldfur))",
      "url": "mxc://matrix.chir.rs/6b0730414bbba1932afb281d5ce0b17a47786860",
      "info": {
        "w": 256,
        "h": 256,
        "size": 75184,
        "mimetype": "image/png",
        "thumbnail_url": "mxc://matrix.chir.rs/6b0730414bbba1932afb281d5ce0b17a47786860",
        "thumbnail_info": {
          "w": 256,
          "h": 256,
          "size": 75184,
          "mimetype": "image/png"
        }
      },
      "msgtype": "m.sticker",
      "id": "tg-528140325818990743",
      "net.maunium.telegram.sticker": {
        "pack": {
          "id": "528140325818990594",
          "short_name": "HeathclawStickers"
        },
        "id": "528140325818990743",
        "emoticons": [
          "😝"
        ]
      }
    },
    {
      "body": "🎵 (Heath (Art by @ReynGoldfur))",
      "url": "mxc://matrix.chir.rs/00b93b56826bb88b6e1e03f97f8a3ce0b3c889c5",
      "info": {
        "w": 256,
        "h": 256,
        "size": 120377,
        "mimetype": "image/png",
        "thumbnail_url": "mxc://matrix.chir.rs/00b93b56826bb88b6e1e03f97f8a3ce0b3c889c5",
        "thumbnail_info": {
          "w": 256,
          "h": 256,
          "size": 120377,
          "mimetype": "image/png"
        }
      },
      "msgtype": "m.sticker",
      "id": "tg-528140325818990744",
      "net.maunium.telegram.sticker": {
        "pack": {
          "id": "528140325818990594",
          "short_name": "HeathclawStickers"
        },
        "id": "528140325818990744",
        "emoticons": [
          "🎵"
        ]
      }
    },
    {
      "body": "😜 (Heath (Art by @ReynGoldfur))",
      "url": "mxc://matrix.chir.rs/c89e9f3637064f990c6aa1fb7578feece5272c79",
      "info": {
        "w": 256,
        "h": 256,
        "size": 83860,
        "mimetype": "image/png",
        "thumbnail_url": "mxc://matrix.chir.rs/c89e9f3637064f990c6aa1fb7578feece5272c79",
        "thumbnail_info": {
          "w": 256,
          "h": 256,
          "size": 83860,
          "mimetype": "image/png"
        }
      },
      "msgtype": "m.sticker",
      "id": "tg-528140325818990745",
      "net.maunium.telegram.sticker": {
        "pack": {
          "id": "528140325818990594",
          "short_name": "HeathclawStickers"
        },
        "id": "528140325818990745",
        "emoticons": [
          "😜"
        ]
      }
    },
    {
      "body": "😽 (Heath (Art by @ReynGoldfur))",
      "url": "mxc://matrix.chir.rs/c37c0df042db11058fc4a33460968e49784a955f",
      "info": {
        "w": 256,
        "h": 256,
        "size": 119089,
        "mimetype": "image/png",
        "thumbnail_url": "mxc://matrix.chir.rs/c37c0df042db11058fc4a33460968e49784a955f",
        "thumbnail_info": {
          "w": 256,
          "h": 256,
          "size": 119089,
          "mimetype": "image/png"
        }
      },
      "msgtype": "m.sticker",
      "id": "tg-528140325818990746",
      "net.maunium.telegram.sticker": {
        "pack": {
          "id": "528140325818990594",
          "short_name": "HeathclawStickers"
        },
        "id": "528140325818990746",
        "emoticons": [
          "😽"
        ]
      }
    },
    {
      "body": "😼 (Heath (Art by @ReynGoldfur))",
      "url": "mxc://matrix.chir.rs/aaa955dfa4c9ddacb37fd9e2f8c3eb461072ec6e",
      "info": {
        "w": 256,
        "h": 256,
        "size": 75683,
        "mimetype": "image/png",
        "thumbnail_url": "mxc://matrix.chir.rs/aaa955dfa4c9ddacb37fd9e2f8c3eb461072ec6e",
        "thumbnail_info": {
          "w": 256,
          "h": 256,
          "size": 75683,
          "mimetype": "image/png"
        }
      },
      "msgtype": "m.sticker",
      "id": "tg-528140325818990747",
      "net.maunium.telegram.sticker": {
        "pack": {
          "id": "528140325818990594",
          "short_name": "HeathclawStickers"
        },
        "id": "528140325818990747",
        "emoticons": [
          "😼"
        ]
      }
    },
    {
      "body": "😅 (Heath (Art by @ReynGoldfur))",
      "url": "mxc://matrix.chir.rs/216750ce84c21a8fa62a7eb977beb76633cab890",
      "info": {
        "w": 256,
        "h": 256,
        "size": 101045,
        "mimetype": "image/png",
        "thumbnail_url": "mxc://matrix.chir.rs/216750ce84c21a8fa62a7eb977beb76633cab890",
        "thumbnail_info": {
          "w": 256,
          "h": 256,
          "size": 101045,
          "mimetype": "image/png"
        }
      },
      "msgtype": "m.sticker",
      "id": "tg-528140325818990748",
      "net.maunium.telegram.sticker": {
        "pack": {
          "id": "528140325818990594",
          "short_name": "HeathclawStickers"
        },
        "id": "528140325818990748",
        "emoticons": [
          "😅"
        ]
      }
    },
    {
      "body": "❤️ (Heath (Art by @ReynGoldfur))",
      "url": "mxc://matrix.chir.rs/55c690ebf17bcac5e06546d7351b069c3090c6f0",
      "info": {
        "w": 256,
        "h": 256,
        "size": 87819,
        "mimetype": "image/png",
        "thumbnail_url": "mxc://matrix.chir.rs/55c690ebf17bcac5e06546d7351b069c3090c6f0",
        "thumbnail_info": {
          "w": 256,
          "h": 256,
          "size": 87819,
          "mimetype": "image/png"
        }
      },
      "msgtype": "m.sticker",
      "id": "tg-528140325818990749",
      "net.maunium.telegram.sticker": {
        "pack": {
          "id": "528140325818990594",
          "short_name": "HeathclawStickers"
        },
        "id": "528140325818990749",
        "emoticons": [
          "❤"
        ]
      }
    },
    {
      "body": "👅 (Heath (Art by @ReynGoldfur))",
      "url": "mxc://matrix.chir.rs/7d76500464b2dc1a509427dda17352dfd9f2ad25",
      "info": {
        "w": 256,
        "h": 256,
        "size": 86935,
        "mimetype": "image/png",
        "thumbnail_url": "mxc://matrix.chir.rs/7d76500464b2dc1a509427dda17352dfd9f2ad25",
        "thumbnail_info": {
          "w": 256,
          "h": 256,
          "size": 86935,
          "mimetype": "image/png"
        }
      },
      "msgtype": "m.sticker",
      "id": "tg-528140325818990750",
      "net.maunium.telegram.sticker": {
        "pack": {
          "id": "528140325818990594",
          "short_name": "HeathclawStickers"
        },
        "id": "528140325818990750",
        "emoticons": [
          "👅"
        ]
      }
    },
    {
      "body": "😂 (Heath (Art by @ReynGoldfur))",
      "url": "mxc://matrix.chir.rs/528e2af00c272cc77ad2765fa2d014320b5ef110",
      "info": {
        "w": 256,
        "h": 256,
        "size": 113359,
        "mimetype": "image/png",
        "thumbnail_url": "mxc://matrix.chir.rs/528e2af00c272cc77ad2765fa2d014320b5ef110",
        "thumbnail_info": {
          "w": 256,
          "h": 256,
          "size": 113359,
          "mimetype": "image/png"
        }
      },
      "msgtype": "m.sticker",
      "id": "tg-528140325818990751",
      "net.maunium.telegram.sticker": {
        "pack": {
          "id": "528140325818990594",
          "short_name": "HeathclawStickers"
        },
        "id": "528140325818990751",
        "emoticons": [
          "😂"
        ]
      }
    },
    {
      "body": "😂 (Heath (Art by @ReynGoldfur))",
      "url": "mxc://matrix.chir.rs/ba1e75adc746829422588ba4d931635d5ced2f14",
      "info": {
        "w": 256,
        "h": 256,
        "size": 97496,
        "mimetype": "image/png",
        "thumbnail_url": "mxc://matrix.chir.rs/ba1e75adc746829422588ba4d931635d5ced2f14",
        "thumbnail_info": {
          "w": 256,
          "h": 256,
          "size": 97496,
          "mimetype": "image/png"
        }
      },
      "msgtype": "m.sticker",
      "id": "tg-528140325818990752",
      "net.maunium.telegram.sticker": {
        "pack": {
          "id": "528140325818990594",
          "short_name": "HeathclawStickers"
        },
        "id": "528140325818990752",
        "emoticons": [
          "😂"
        ]
      }
    },
    {
      "body": "😐 (Heath (Art by @ReynGoldfur))",
      "url": "mxc://matrix.chir.rs/86e7e691a0dc8227b3dd7aa1752cb7acbc0ef4da",
      "info": {
        "w": 256,
        "h": 256,
        "size": 86668,
        "mimetype": "image/png",
        "thumbnail_url": "mxc://matrix.chir.rs/86e7e691a0dc8227b3dd7aa1752cb7acbc0ef4da",
        "thumbnail_info": {
          "w": 256,
          "h": 256,
          "size": 86668,
          "mimetype": "image/png"
        }
      },
      "msgtype": "m.sticker",
      "id": "tg-528140325818990753",
      "net.maunium.telegram.sticker": {
        "pack": {
          "id": "528140325818990594",
          "short_name": "HeathclawStickers"
        },
        "id": "528140325818990753",
        "emoticons": [
          "😐"
        ]
      }
    },
    {
      "body": "😒 (Heath (Art by @ReynGoldfur))",
      "url": "mxc://matrix.chir.rs/54af4b53999df8bd91ba1b1b82d6a636cc501b7c",
      "info": {
        "w": 256,
        "h": 256,
        "size": 98942,
        "mimetype": "image/png",
        "thumbnail_url": "mxc://matrix.chir.rs/54af4b53999df8bd91ba1b1b82d6a636cc501b7c",
        "thumbnail_info": {
          "w": 256,
          "h": 256,
          "size": 98942,
          "mimetype": "image/png"
        }
      },
      "msgtype": "m.sticker",
      "id": "tg-528140325818990754",
      "net.maunium.telegram.sticker": {
        "pack": {
          "id": "528140325818990594",
          "short_name": "HeathclawStickers"
        },
        "id": "528140325818990754",
        "emoticons": [
          "😒"
        ]
      }
    },
    {
      "body": "😤 (Heath (Art by @ReynGoldfur))",
      "url": "mxc://matrix.chir.rs/27f75c804403233d23e40af99b5a7781f66ab9bd",
      "info": {
        "w": 256,
        "h": 256,
        "size": 95787,
        "mimetype": "image/png",
        "thumbnail_url": "mxc://matrix.chir.rs/27f75c804403233d23e40af99b5a7781f66ab9bd",
        "thumbnail_info": {
          "w": 256,
          "h": 256,
          "size": 95787,
          "mimetype": "image/png"
        }
      },
      "msgtype": "m.sticker",
      "id": "tg-528140325818990755",
      "net.maunium.telegram.sticker": {
        "pack": {
          "id": "528140325818990594",
          "short_name": "HeathclawStickers"
        },
        "id": "528140325818990755",
        "emoticons": [
          "😤"
        ]
      }
    },
    {
      "body": "😈 (Heath (Art by @ReynGoldfur))",
      "url": "mxc://matrix.chir.rs/d45fa8fb0488b9e406a5803c45db0bcb857572e0",
      "info": {
        "w": 256,
        "h": 256,
        "size": 87415,
        "mimetype": "image/png",
        "thumbnail_url": "mxc://matrix.chir.rs/d45fa8fb0488b9e406a5803c45db0bcb857572e0",
        "thumbnail_info": {
          "w": 256,
          "h": 256,
          "size": 87415,
          "mimetype": "image/png"
        }
      },
      "msgtype": "m.sticker",
      "id": "tg-528140325818990756",
      "net.maunium.telegram.sticker": {
        "pack": {
          "id": "528140325818990594",
          "short_name": "HeathclawStickers"
        },
        "id": "528140325818990756",
        "emoticons": [
          "😈"
        ]
      }
    },
    {
      "body": "💦 (Heath (Art by @ReynGoldfur))",
      "url": "mxc://matrix.chir.rs/e92427828088a8efe825fa978789ef54576db744",
      "info": {
        "w": 256,
        "h": 256,
        "size": 119596,
        "mimetype": "image/png",
        "thumbnail_url": "mxc://matrix.chir.rs/e92427828088a8efe825fa978789ef54576db744",
        "thumbnail_info": {
          "w": 256,
          "h": 256,
          "size": 119596,
          "mimetype": "image/png"
        }
      },
      "msgtype": "m.sticker",
      "id": "tg-528140325818990757",
      "net.maunium.telegram.sticker": {
        "pack": {
          "id": "528140325818990594",
          "short_name": "HeathclawStickers"
        },
        "id": "528140325818990757",
        "emoticons": [
          "💦"
        ]
      }
    },
    {
      "body": "😓 (Heath (Art by @ReynGoldfur))",
      "url": "mxc://matrix.chir.rs/01ad7706f0a8dd0903e5686465aae9a7910042c4",
      "info": {
        "w": 256,
        "h": 256,
        "size": 191467,
        "mimetype": "image/png",
        "thumbnail_url": "mxc://matrix.chir.rs/01ad7706f0a8dd0903e5686465aae9a7910042c4",
        "thumbnail_info": {
          "w": 256,
          "h": 256,
          "size": 191467,
          "mimetype": "image/png"
        }
      },
      "msgtype": "m.sticker",
      "id": "tg-528140325818990759",
      "net.maunium.telegram.sticker": {
        "pack": {
          "id": "528140325818990594",
          "short_name": "HeathclawStickers"
        },
        "id": "528140325818990759",
        "emoticons": [
          "😓"
        ]
      }
    },
    {
      "body": "❔ (Heath (Art by @ReynGoldfur))",
      "url": "mxc://matrix.chir.rs/7e4885cbcc0beb791fadf9c9bb7eaf45a700b330",
      "info": {
        "w": 256,
        "h": 256,
        "size": 120568,
        "mimetype": "image/png",
        "thumbnail_url": "mxc://matrix.chir.rs/7e4885cbcc0beb791fadf9c9bb7eaf45a700b330",
        "thumbnail_info": {
          "w": 256,
          "h": 256,
          "size": 120568,
          "mimetype": "image/png"
        }
      },
      "msgtype": "m.sticker",
      "id": "tg-528140325818990760",
      "net.maunium.telegram.sticker": {
        "pack": {
          "id": "528140325818990594",
          "short_name": "HeathclawStickers"
        },
        "id": "528140325818990760",
        "emoticons": [
          "❔"
        ]
      }
    },
    {
      "body": "🧶 (Heath (Art by @ReynGoldfur))",
      "url": "mxc://matrix.chir.rs/6b53896f9faf0fcd4c1fa546bd369e4530f5a0b6",
      "info": {
        "w": 256,
        "h": 256,
        "size": 166283,
        "mimetype": "image/png",
        "thumbnail_url": "mxc://matrix.chir.rs/6b53896f9faf0fcd4c1fa546bd369e4530f5a0b6",
        "thumbnail_info": {
          "w": 256,
          "h": 256,
          "size": 166283,
          "mimetype": "image/png"
        }
      },
      "msgtype": "m.sticker",
      "id": "tg-528140325818990761",
      "net.maunium.telegram.sticker": {
        "pack": {
          "id": "528140325818990594",
          "short_name": "HeathclawStickers"
        },
        "id": "528140325818990761",
        "emoticons": [
          "🧶"
        ]
      }
    },
    {
      "body": "😠 (Heath (Art by @ReynGoldfur))",
      "url": "mxc://matrix.chir.rs/1081d57bbc2806d15de82cc8b1aca54680f71252",
      "info": {
        "w": 256,
        "h": 256,
        "size": 129308,
        "mimetype": "image/png",
        "thumbnail_url": "mxc://matrix.chir.rs/1081d57bbc2806d15de82cc8b1aca54680f71252",
        "thumbnail_info": {
          "w": 256,
          "h": 256,
          "size": 129308,
          "mimetype": "image/png"
        }
      },
      "msgtype": "m.sticker",
      "id": "tg-528140325818990762",
      "net.maunium.telegram.sticker": {
        "pack": {
          "id": "528140325818990594",
          "short_name": "HeathclawStickers"
        },
        "id": "528140325818990762",
        "emoticons": [
          "😠"
        ]
      }
    },
    {
      "body": "😡 (Heath (Art by @ReynGoldfur))",
      "url": "mxc://matrix.chir.rs/aa04c169c176efab4a7c5edbdfde324d9d695597",
      "info": {
        "w": 256,
        "h": 256,
        "size": 126797,
        "mimetype": "image/png",
        "thumbnail_url": "mxc://matrix.chir.rs/aa04c169c176efab4a7c5edbdfde324d9d695597",
        "thumbnail_info": {
          "w": 256,
          "h": 256,
          "size": 126797,
          "mimetype": "image/png"
        }
      },
      "msgtype": "m.sticker",
      "id": "tg-528140325818990763",
      "net.maunium.telegram.sticker": {
        "pack": {
          "id": "528140325818990594",
          "short_name": "HeathclawStickers"
        },
        "id": "528140325818990763",
        "emoticons": [
          "😡"
        ]
      }
    },
    {
      "body": "😿 (Heath (Art by @ReynGoldfur))",
      "url": "mxc://matrix.chir.rs/58af70b06b942a47ef618a1698fcf559ea266dd1",
      "info": {
        "w": 256,
        "h": 256,
        "size": 84286,
        "mimetype": "image/png",
        "thumbnail_url": "mxc://matrix.chir.rs/58af70b06b942a47ef618a1698fcf559ea266dd1",
        "thumbnail_info": {
          "w": 256,
          "h": 256,
          "size": 84286,
          "mimetype": "image/png"
        }
      },
      "msgtype": "m.sticker",
      "id": "tg-5044090161713906255",
      "net.maunium.telegram.sticker": {
        "pack": {
          "id": "528140325818990594",
          "short_name": "HeathclawStickers"
        },
        "id": "5044090161713906255",
        "emoticons": [
          "😿"
        ]
      }
    },
    {
      "body": "👅 (Heath (Art by @ReynGoldfur))",
      "url": "mxc://matrix.chir.rs/c1064cee8a1494c6e525aae73e25d2488d639699",
      "info": {
        "w": 256,
        "h": 256,
        "size": 103228,
        "mimetype": "image/png",
        "thumbnail_url": "mxc://matrix.chir.rs/c1064cee8a1494c6e525aae73e25d2488d639699",
        "thumbnail_info": {
          "w": 256,
          "h": 256,
          "size": 103228,
          "mimetype": "image/png"
        }
      },
      "msgtype": "m.sticker",
      "id": "tg-5044594042982105640",
      "net.maunium.telegram.sticker": {
        "pack": {
          "id": "528140325818990594",
          "short_name": "HeathclawStickers"
        },
        "id": "5044594042982105640",
        "emoticons": [
          "👅"
        ]
      }
    },
    {
      "body": "✊ (Heath (Art by @ReynGoldfur))",
      "url": "mxc://matrix.chir.rs/07ea1738a94980dbb829ebf64807743192137b23",
      "info": {
        "w": 256,
        "h": 256,
        "size": 105481,
        "mimetype": "image/png",
        "thumbnail_url": "mxc://matrix.chir.rs/07ea1738a94980dbb829ebf64807743192137b23",
        "thumbnail_info": {
          "w": 256,
          "h": 256,
          "size": 105481,
          "mimetype": "image/png"
        }
      },
      "msgtype": "m.sticker",
      "id": "tg-5044376563018105888",
      "net.maunium.telegram.sticker": {
        "pack": {
          "id": "528140325818990594",
          "short_name": "HeathclawStickers"
        },
        "id": "5044376563018105888",
        "emoticons": [
          "✊"
        ]
      }
    },
    {
      "body": "© (Heath (Art by @ReynGoldfur))",
      "url": "mxc://matrix.chir.rs/9ae26aa082efeb33a84b9f71e8b7ffb5b2722fc8",
      "info": {
        "w": 256,
        "h": 256,
        "size": 123544,
        "mimetype": "image/png",
        "thumbnail_url": "mxc://matrix.chir.rs/9ae26aa082efeb33a84b9f71e8b7ffb5b2722fc8",
        "thumbnail_info": {
          "w": 256,
          "h": 256,
          "size": 123544,
          "mimetype": "image/png"
        }
      },
      "msgtype": "m.sticker",
      "id": "tg-528140325818990700",
      "net.maunium.telegram.sticker": {
        "pack": {
          "id": "528140325818990594",
          "short_name": "HeathclawStickers"
        },
        "id": "528140325818990700",
        "emoticons": [
          "©"
        ]
      }
    }
  ]
}
